sts2credentials/__init__.py
sts2credentials/__main__.py
sts2credentials-0.1.1.dist-info/LICENSE
sts2credentials-0.1.1.dist-info/METADATA
sts2credentials-0.1.1.dist-info/WHEEL
sts2credentials-0.1.1.dist-info/entry_points.txt
sts2credentials-0.1.1.dist-info/top_level.txt
sts2credentials-0.1.1.dist-info/RECORD
